sph/__init__.py
sph/command.py
sph/editable.py
sph/utils.py
sph-2.0.9.dist-info/LICENSE
sph-2.0.9.dist-info/METADATA
sph-2.0.9.dist-info/WHEEL
sph-2.0.9.dist-info/entry_points.txt
sph-2.0.9.dist-info/RECORD
